thread_regulator/__init__.py
thread_regulator/__main__.py
thread_regulator/graphs/__init__.py
thread_regulator/graphs/drag_drop_dashboard.py
thread_regulator/graphs/performance_graphs.py
thread_regulator/graphs/tabbed_dashboard.py
thread_regulator_pjn2work-0.2.5.dist-info/LICENSE
thread_regulator_pjn2work-0.2.5.dist-info/METADATA
thread_regulator_pjn2work-0.2.5.dist-info/WHEEL
thread_regulator_pjn2work-0.2.5.dist-info/top_level.txt
thread_regulator_pjn2work-0.2.5.dist-info/RECORD
