Metadata-Version: 2.1
Name: thread-regulator-pjn2work
Version: 0.2.5
Summary: Thread Regulator with notifications and statistics
Home-page: https://github.com/pjn2work/thread_regulator
Author: Pedro Jorge Nunes
Author-email: pjn2work@google.com
License: UNKNOWN
Platform: UNKNOWN
Classifier: Programming Language :: Python :: 3
Classifier: License :: OSI Approved :: MIT License
Classifier: Operating System :: OS Independent
Requires-Python: >=3.6
Requires-Dist: pandas (>=1.0.1)
Requires-Dist: xlsxwriter (>=1.2.9)
Requires-Dist: openpyxl (>=3.0.4)
Requires-Dist: dash (>=2.0.0)
Requires-Dist: dash-bootstrap-components (>=1.0.0)
